pypp/LICENSE.txt
pypp/__init__.py
pypp/evaluator.py
pypp/lextab.py
pypp/parser.py
pypp/pcmd.py
pypp/preprocessor.py
pypp/pickled/lex.pickle
pypp/pickled/yacc.pickle
pypp/ply/src/ply/__init__.py
pypp/ply/src/ply/lex.py
pypp/ply/src/ply/yacc.py
pypp_for_pwcp-1.33b5.dist-info/LICENSE.txt
pypp_for_pwcp-1.33b5.dist-info/METADATA
pypp_for_pwcp-1.33b5.dist-info/WHEEL
pypp_for_pwcp-1.33b5.dist-info/entry_points.txt
pypp_for_pwcp-1.33b5.dist-info/top_level.txt
pypp_for_pwcp-1.33b5.dist-info/RECORD
