Metadata-Version: 2.1
Name: pypp-for-pwcp
Version: 1.33b5
Summary: A C99-like preprocessor for Python
Home-page: https://github.com/solaluset/pypp
Author: Niall Douglas and David Beazley
License: BSD
Classifier: Development Status :: 5 - Production/Stable
Classifier: Intended Audience :: Developers
Classifier: Topic :: Software Development :: Build Tools
Classifier: License :: OSI Approved :: BSD License
Classifier: Programming Language :: Python :: 3
License-File: LICENSE.txt
